qaspen/__init__.py
qaspen/__main__.py
qaspen/abc/__init__.py
qaspen/abc/abc_types.py
qaspen/abc/db_engine.py
qaspen/abc/db_transaction.py
qaspen/aggregate_functions/__init__.py
qaspen/aggregate_functions/base.py
qaspen/aggregate_functions/general_purpose.py
qaspen/base/__init__.py
qaspen/base/comparison_operators.py
qaspen/base/operators.py
qaspen/base/sql_base.py
qaspen/base/text.py
qaspen/clauses/__init__.py
qaspen/clauses/filter.py
qaspen/clauses/order_by.py
qaspen/columns/__init__.py
qaspen/columns/aliases.py
qaspen/columns/base.py
qaspen/columns/complex.py
qaspen/columns/operators.py
qaspen/columns/primitive.py
qaspen/config.py
qaspen/exceptions.py
qaspen/py.typed
qaspen/qaspen_types.py
qaspen/querystring/__init__.py
qaspen/querystring/querystring.py
qaspen/sql_type/__init__.py
qaspen/sql_type/base.py
qaspen/sql_type/complex_types.py
qaspen/sql_type/mapper.py
qaspen/sql_type/primitive_types.py
qaspen/statements/__init__.py
qaspen/statements/base.py
qaspen/statements/combinable_statements/__init__.py
qaspen/statements/combinable_statements/combinations.py
qaspen/statements/combinable_statements/filter_statement.py
qaspen/statements/combinable_statements/join_statement.py
qaspen/statements/combinable_statements/order_by_statement.py
qaspen/statements/delete_statement.py
qaspen/statements/exists_statement.py
qaspen/statements/insert_statement.py
qaspen/statements/intersect_statement.py
qaspen/statements/select_statement.py
qaspen/statements/statement.py
qaspen/statements/statement_result/__init__.py
qaspen/statements/statement_result/result_variants.py
qaspen/statements/statement_result/select_statement_result.py
qaspen/statements/sub_statements/__init__.py
qaspen/statements/sub_statements/group_by_statement.py
qaspen/statements/sub_statements/limit_statement.py
qaspen/statements/sub_statements/offset_statement.py
qaspen/statements/union_statement.py
qaspen/statements/update_statement.py
qaspen/table/__init__.py
qaspen/table/base_table.py
qaspen-0.0.16a0.dist-info/METADATA
qaspen-0.0.16a0.dist-info/WHEEL
qaspen-0.0.16a0.dist-info/RECORD
