Metadata-Version: 2.1
Name: qaspen
Version: 0.0.16a0
Summary: 
Author: chandr-andr (Kiselev Aleksandr)
Author-email: askiselev00@gmail.com
Requires-Python: >=3.8.1,<4.0
Classifier: Programming Language :: Python :: 3
Classifier: Programming Language :: Python :: 3.9
Classifier: Programming Language :: Python :: 3.10
Classifier: Programming Language :: Python :: 3.11
Classifier: Programming Language :: Python :: 3.12
Requires-Dist: msgspec (>=0.18.4,<0.19.0)
Requires-Dist: pydantic (>=2.4.2,<3.0.0)
Requires-Dist: qaspen-psycopg (>=0.0.9a0,<0.0.10)
Requires-Dist: tomlkit (>=0.12.3,<0.13.0)
